aiogc/__init__.py
aiogc/events.py
aiogc/free_busy.py
aiogc/helpers.py
aiogc/models.py
aiogc-0.1.5.dist-info/LICENSE
aiogc-0.1.5.dist-info/METADATA
aiogc-0.1.5.dist-info/WHEEL
aiogc-0.1.5.dist-info/top_level.txt
aiogc-0.1.5.dist-info/RECORD
