Metadata-Version: 2.1
Name: aiogc
Version: 0.1.5
Summary: Async Google Calendar API Client
Home-page: https://github.com/mitinarseny/aiogc
Author: Arseny Mitin
Author-email: mitinarseny@gmail.com
License: UNKNOWN
Platform: UNKNOWN
Classifier: Programming Language :: Python :: 3.7
Classifier: License :: OSI Approved :: MIT License
Classifier: Operating System :: OS Independent
